microsoftoauth/__init__.py
microsoftoauth-1.0.0.dist-info/METADATA
microsoftoauth-1.0.0.dist-info/WHEEL
microsoftoauth-1.0.0.dist-info/top_level.txt
microsoftoauth-1.0.0.dist-info/RECORD
