Metadata-Version: 2.1
Name: microsoftoauth
Version: 1.0.0
Summary: Oauth
Home-page: UNKNOWN
Author: ЕntchenBuilds
Author-email: ЕntchenBuilds@gmail.com
License: UNKNOWN
Keywords: python
Platform: UNKNOWN
Classifier: Operating System :: Microsoft :: Windows
